<ArrayOfNode>
  <Node>
    <Name>1</Name>
    <isTracked>false</isTracked>
    <TagId>1</TagId>
    <ConnectedNodes>
      <NodeConnection>
        <To>2</To>
        <IsWheelchairAccessible>true</IsWheelchairAccessible>
        <Relative_x>3.087533</Relative_x>
        <Relative_y>-0.1501317</Relative_y>
        <Relative_z>-1.35732794</Relative_z>
      </NodeConnection>
      <NodeConnection>
        <To>mak</To>
        <IsWheelchairAccessible>true</IsWheelchairAccessible>
        <Relative_x>-0.479509473</Relative_x>
        <Relative_y>-0.13701123</Relative_y>
        <Relative_z>-2.2254982</Relative_z>
      </NodeConnection>
      <NodeConnection>
        <To>regal</To>
        <IsWheelchairAccessible>true</IsWheelchairAccessible>
        <Relative_x>0.0142130852</Relative_x>
        <Relative_y>-0.0267577171</Relative_y>
        <Relative_z>2.08809972</Relative_z>
      </NodeConnection>
      <NodeConnection>
        <To>biorko 2</To>
        <IsWheelchairAccessible>true</IsWheelchairAccessible>
        <Relative_x>1.09060884</Relative_x>
        <Relative_y>-0.1317698</Relative_y>
        <Relative_z>2.04686928</Relative_z>
      </NodeConnection>
    </ConnectedNodes>
  </Node>
  <Node>
    <Name>2</Name>
    <isTracked>false</isTracked>
    <TagId>2</TagId>
    <ConnectedNodes>
      <NodeConnection>
        <To>1</To>
        <IsWheelchairAccessible>true</IsWheelchairAccessible>
        <Relative_x>-3.087533</Relative_x>
        <Relative_y>0.1501317</Relative_y>
        <Relative_z>1.35732794</Relative_z>
      </NodeConnection>
      <NodeConnection>
        <To>drukarka</To>
        <IsWheelchairAccessible>true</IsWheelchairAccessible>
        <Relative_x>0.157778025</Relative_x>
        <Relative_y>0.0335885137</Relative_y>
        <Relative_z>1.47542131</Relative_z>
      </NodeConnection>
      <NodeConnection>
        <To>biorko 1</To>
        <IsWheelchairAccessible>true</IsWheelchairAccessible>
        <Relative_x>-1.98549676</Relative_x>
        <Relative_y>-0.0302543342</Relative_y>
        <Relative_z>3.38405371</Relative_z>
      </NodeConnection>
    </ConnectedNodes>
  </Node>
  <Node>
    <Name>drukarka</Name>
    <isTracked>false</isTracked>
    <ConnectedNodes>
      <NodeConnection>
        <To>2</To>
        <IsWheelchairAccessible>true</IsWheelchairAccessible>
        <Relative_x>-0.157778025</Relative_x>
        <Relative_y>-0.0335885137</Relative_y>
        <Relative_z>-1.47542131</Relative_z>
      </NodeConnection>
    </ConnectedNodes>
  </Node>
  <Node>
    <Name>biorko 1</Name>
    <isTracked>false</isTracked>
    <ConnectedNodes>
      <NodeConnection>
        <To>2</To>
        <IsWheelchairAccessible>true</IsWheelchairAccessible>
        <Relative_x>1.98549676</Relative_x>
        <Relative_y>0.0302543342</Relative_y>
        <Relative_z>-3.38405371</Relative_z>
      </NodeConnection>
    </ConnectedNodes>
  </Node>
  <Node>
    <Name>mak</Name>
    <isTracked>false</isTracked>
    <ConnectedNodes>
      <NodeConnection>
        <To>1</To>
        <IsWheelchairAccessible>true</IsWheelchairAccessible>
        <Relative_x>0.479509473</Relative_x>
        <Relative_y>0.13701123</Relative_y>
        <Relative_z>2.2254982</Relative_z>
      </NodeConnection>
    </ConnectedNodes>
  </Node>
  <Node>
    <Name>regal</Name>
    <isTracked>false</isTracked>
    <ConnectedNodes>
      <NodeConnection>
        <To>1</To>
        <IsWheelchairAccessible>true</IsWheelchairAccessible>
        <Relative_x>-0.0142130852</Relative_x>
        <Relative_y>0.0267577171</Relative_y>
        <Relative_z>-2.08809972</Relative_z>
      </NodeConnection>
    </ConnectedNodes>
  </Node>
  <Node>
    <Name>biorko 2</Name>
    <isTracked>false</isTracked>
    <ConnectedNodes>
      <NodeConnection>
        <To>1</To>
        <IsWheelchairAccessible>true</IsWheelchairAccessible>
        <Relative_x>-1.09060884</Relative_x>
        <Relative_y>0.1317698</Relative_y>
        <Relative_z>-2.04686928</Relative_z>
      </NodeConnection>
    </ConnectedNodes>
  </Node>
</ArrayOfNode>